LICENSE
README.md
setup.py
src/blockchain_lab/__init__.py
src/blockchain_lab/blockchain_lab.py
src/blockchain_lab.egg-info/PKG-INFO
src/blockchain_lab.egg-info/SOURCES.txt
src/blockchain_lab.egg-info/dependency_links.txt
src/blockchain_lab.egg-info/entry_points.txt
src/blockchain_lab.egg-info/not-zip-safe
src/blockchain_lab.egg-info/top_level.txt