Metadata-Version: 2.1
Name: blockchain-lab
Version: 0.5.0
Summary: A fully functional blockchain lab.
Home-page: https://github.com/Decentra-Network/Blockchain-Lab
Author: Decentra Network Developers
Author-email: onur@decentranetwork.org
License: MPL-2.0
Platform: UNKNOWN
Requires-Python: >=3.6
License-File: LICENSE
